uikitpy.cp312-win_amd64.pyd
uikitpy-0.2.0.dist-info/METADATA
uikitpy-0.2.0.dist-info/WHEEL
uikitpy-0.2.0.dist-info/entry_points.txt
uikitpy-0.2.0.dist-info/licenses/LICENSE
uikitpy-0.2.0.dist-info/RECORD
