Metadata-Version: 2.1
Name: uikitpy
Version: 0.2.0
Summary: A set of libraries for UI development.
Author-Email: Taylor Holberton <taylorcholberton@gmail.com>
Classifier: Development Status :: 4 - Beta
Classifier: License :: OSI Approved :: Apache Software License
Classifier: Programming Language :: Python :: 3 :: Only
Classifier: Programming Language :: Python :: 3.7
Classifier: Programming Language :: Python :: 3.8
Classifier: Programming Language :: Python :: 3.9
Classifier: Programming Language :: Python :: 3.10
Classifier: Programming Language :: Python :: 3.11
Classifier: Programming Language :: Python :: 3.12
Project-URL: Homepage, https://github.com/tay10r/uikit
Project-URL: Issues, https://github.com/tay10r/uikit/issues
